hslSixColor/__init__.py
hslSixColor/main.py
hslSixColor-0.1.5.dist-info/LICENSE.txt
hslSixColor-0.1.5.dist-info/METADATA
hslSixColor-0.1.5.dist-info/WHEEL
hslSixColor-0.1.5.dist-info/top_level.txt
hslSixColor-0.1.5.dist-info/RECORD
