Metadata-Version: 2.1
Name: hslSixColor
Version: 0.1.5
Summary: A package for image processing with HSL color adjustment and error diffusion dithering
Home-page: https://github.com/yourusername/hsl-six-color
Author: Nayi
Author-email: 202308131171@stu.cqu.edu.cn
Requires-Python: >=3.7
License-File: LICENSE.txt
Requires-Dist: numpy
Requires-Dist: pillow
